MANIFEST.in
setup.cfg
setup.py
tombstones/__init__.py
tombstones/__main__.py
tombstones/analysis.py
tombstones/decorator.py
tombstones/log.py
tombstones/tombstones.log
tombstones.egg-info/PKG-INFO
tombstones.egg-info/SOURCES.txt
tombstones.egg-info/dependency_links.txt
tombstones.egg-info/entry_points.txt
tombstones.egg-info/requires.txt
tombstones.egg-info/top_level.txt