Metadata-Version: 1.1
Name: tombstones
Version: 0.1
Summary: Python package to mark dead code.
Home-page: https://github.com/perclasson/python-tombstones
Author: Per Classon
Author-email: perwclasson@gmail.com
License: BSD
Download-URL: https://github.com/perclasson/python-tombstones/tarball/0.1
Keywords: dead code,unreachable code
Platform: UNKNOWN
